{
  "version": "1.0.0",
  "lastScanned": 1775716396113,
  "projectRoot": "/Users/singyuseob/medicalkoreaguide",
  "techStack": {
    "languages": [
      {
        "name": "JavaScript/TypeScript",
        "version": null,
        "confidence": "high",
        "markers": [
          "package.json"
        ]
      },
      {
        "name": "TypeScript",
        "version": null,
        "confidence": "high",
        "markers": [
          "tsconfig.json"
        ]
      }
    ],
    "frameworks": [
      {
        "name": "next",
        "version": "16.2.0",
        "category": "fullstack"
      },
      {
        "name": "react",
        "version": "19.2.4",
        "category": "frontend"
      },
      {
        "name": "react-dom",
        "version": "19.2.4",
        "category": "frontend"
      }
    ],
    "packageManager": "npm",
    "runtime": null
  },
  "build": {
    "buildCommand": "npm run build",
    "testCommand": null,
    "lintCommand": "npm run lint",
    "devCommand": "npm run dev",
    "scripts": {
      "dev": "next dev --webpack",
      "build": "next build",
      "start": "next start",
      "lint": "eslint"
    }
  },
  "conventions": {
    "namingStyle": null,
    "importStyle": null,
    "testPattern": null,
    "fileOrganization": null
  },
  "structure": {
    "isMonorepo": false,
    "workspaces": [],
    "mainDirectories": [
      "public",
      "src"
    ],
    "gitBranches": null
  },
  "customNotes": [],
  "directoryMap": {
    "public": {
      "path": "public",
      "purpose": "Public files",
      "fileCount": 13,
      "lastAccessed": 1775716396001,
      "keyFiles": [
        "AGENTS.md",
        "c3452bc6ba68afc0a9746c8a940551a6.txt",
        "df4cc1b543e52b6b71f0ef8f18fe4e80.txt",
        "file.svg",
        "globe.svg"
      ]
    },
    "src": {
      "path": "src",
      "purpose": "Source code",
      "fileCount": 2,
      "lastAccessed": 1775716396033,
      "keyFiles": [
        "AGENTS.md"
      ]
    },
    "src/app": {
      "path": "src/app",
      "purpose": "Application code",
      "fileCount": 7,
      "lastAccessed": 1775716396089,
      "keyFiles": [
        "AGENTS.md",
        "apple-icon.png",
        "favicon.ico"
      ]
    },
    "src/lib": {
      "path": "src/lib",
      "purpose": "Library code",
      "fileCount": 13,
      "lastAccessed": 1775716396090,
      "keyFiles": [
        "AGENTS.md",
        "articles.ts",
        "firebase.ts"
      ]
    }
  },
  "hotPaths": [
    {
      "path": "src/app/[lang]/[category]/[slug]/page.tsx",
      "accessCount": 9,
      "lastAccessed": 1775717065035,
      "type": "file"
    },
    {
      "path": "src/app/[lang]/[category]/page.tsx",
      "accessCount": 7,
      "lastAccessed": 1775717066881,
      "type": "file"
    },
    {
      "path": "",
      "accessCount": 4,
      "lastAccessed": 1775716491420,
      "type": "directory"
    },
    {
      "path": "src/app/[lang]/page.tsx",
      "accessCount": 4,
      "lastAccessed": 1775716863553,
      "type": "file"
    },
    {
      "path": "src/app/[lang]/layout.tsx",
      "accessCount": 4,
      "lastAccessed": 1775717054198,
      "type": "file"
    },
    {
      "path": "src/app/[lang]/dental/pricing/page.tsx",
      "accessCount": 4,
      "lastAccessed": 1775717068781,
      "type": "file"
    },
    {
      "path": "src/app",
      "accessCount": 3,
      "lastAccessed": 1775716859742,
      "type": "directory"
    },
    {
      "path": "public/robots.txt",
      "accessCount": 3,
      "lastAccessed": 1775717022632,
      "type": "file"
    },
    {
      "path": "vercel.json",
      "accessCount": 3,
      "lastAccessed": 1775717041802,
      "type": "file"
    },
    {
      "path": "src/app/[lang]/dermatology/pricing/page.tsx",
      "accessCount": 3,
      "lastAccessed": 1775717083722,
      "type": "file"
    },
    {
      "path": "src/app/layout.tsx",
      "accessCount": 2,
      "lastAccessed": 1775716884883,
      "type": "file"
    },
    {
      "path": "src/lib/i18n.ts",
      "accessCount": 1,
      "lastAccessed": 1775716495218,
      "type": "file"
    },
    {
      "path": "src/app/page.tsx",
      "accessCount": 1,
      "lastAccessed": 1775716506831,
      "type": "file"
    },
    {
      "path": "next.config.ts",
      "accessCount": 1,
      "lastAccessed": 1775716856456,
      "type": "file"
    },
    {
      "path": "indexnow-submit.js",
      "accessCount": 1,
      "lastAccessed": 1775716856793,
      "type": "file"
    },
    {
      "path": "src/app/api/sitemap/route.ts",
      "accessCount": 1,
      "lastAccessed": 1775716862890,
      "type": "file"
    },
    {
      "path": "public/c3452bc6ba68afc0a9746c8a940551a6.txt",
      "accessCount": 1,
      "lastAccessed": 1775716890181,
      "type": "file"
    },
    {
      "path": "src/app/api/indexnow/route.ts",
      "accessCount": 1,
      "lastAccessed": 1775716895028,
      "type": "file"
    },
    {
      "path": "src/app/components/PricingPage.tsx",
      "accessCount": 1,
      "lastAccessed": 1775716900207,
      "type": "file"
    }
  ],
  "userDirectives": []
}